4bit_ALU_Project/alu.v
module alu(
    input [3:0] A,
    input [3:0] B,
    input [2:0] select,
    output reg [3:0] result
);

always @(*) begin

    case(select)

    3'b000: result = A + B;
    3'b001: result = A - B;
    3'b010: result = A & B;
    3'b011: result = A | B;
    3'b100: result = A ^ B;
    3'b101: result = ~A;
    3'b110: result = A << 1;
    3'b111: result = A >> 1;

    endcase

end

endmodule

4bit_ALU_Project/testbench.v
module testbench;

reg [3:0] A, B;
reg [2:0] select;

wire [3:0] result;

alu uut(
    .A(A),
    .B(B),
    .select(select),
    .result(result)
);

initial begin

$dumpfile("dump.vcd");
$dumpvars(0,testbench);

A = 4'b1010;
B = 4'b0011;

select = 3'b000; #10;
select = 3'b001; #10;
select = 3'b010; #10;
select = 3'b011; #10;
select = 3'b100; #10;
select = 3'b101; #10;
select = 3'b110; #10;
select = 3'b111; #10;

$finish;

end

endmodule

4bit_ALU_Project/dump.vcd
$date
	Wed May 13 18:55:19 2026
$end
$version
	Icarus Verilog
$end
$timescale
	1s
$end
$scope module testbench $end
$var wire 4 ! result [3:0] $end
$var reg 4 " A [3:0] $end
$var reg 4 # B [3:0] $end
$var reg 3 $ select [2:0] $end
$scope module uut $end
$var wire 4 % A [3:0] $end
$var wire 4 & B [3:0] $end
$var wire 3 ' select [2:0] $end
$var reg 4 ( result [3:0] $end
$upscope $end
$upscope $end
$enddefinitions $end
$comment Show the parameter values. $end
$dumpall
$end
#0
$dumpvars
b1101 (
b0 '
b11 &
b1010 %
b0 $
b11 #
b1010 "
b1101 !
$end
#10
b111 !
b111 (
b1 $
b1 '
#20
b10 !
b10 (
b10 $
b10 '
#30
b1011 !
b1011 (
b11 $
b11 '
#40
b1001 !
b1001 (
b100 $
b100 '
#50
b101 !
b101 (
b101 $
b101 '
#60
b100 !
b100 (
b110 $
b110 '
#70
b101 !
b101 (
b111 $
b111 '
